[
  {
    "question": "Как записаться на приём",
    "answer": "Нажмите кнопку 'Записаться' в меню, укажите дату, время и телефон. Мы подтвердим в течение часа."
  },
  {
    "question": "Цены и прайс",
    "answer": "Стрижка от 1500 руб, окрашивание от 3000 руб. Полный прайс-лист доступен на нашем сайте."
  },
  {
    "question": "Адрес и как добраться",
    "answer": "Москва, ул. Пушкина 10, 2 этаж. Метро Тверская, 5 минут пешком. Парковка во дворе."
  },
  {
    "question": "Время работы",
    "answer": "Работаем ежедневно с 10:00 до 20:00. В праздники график может меняться."
  },
  {
    "question": "Возврат и отмена записи",
    "answer": "Отменить запись можно за 2 часа до визита без штрафа. Позвоните или напишите нам."
  }
]
